workos/__about__.py
workos/__init__.py
workos/_base_client.py
workos/_client_configuration.py
workos/api_keys.py
workos/async_client.py
workos/audit_logs.py
workos/client.py
workos/directory_sync.py
workos/events.py
workos/exceptions.py
workos/fga.py
workos/mfa.py
workos/organization_domains.py
workos/organizations.py
workos/passwordless.py
workos/portal.py
workos/py.typed
workos/session.py
workos/sso.py
workos/user_management.py
workos/vault.py
workos/webhooks.py
workos/widgets.py
workos/types/__init__.py
workos/types/list_resource.py
workos/types/metadata.py
workos/types/workos_model.py
workos/types/api_keys/__init__.py
workos/types/api_keys/api_keys.py
workos/types/audit_logs/__init__.py
workos/types/audit_logs/audit_log_event.py
workos/types/audit_logs/audit_log_event_actor.py
workos/types/audit_logs/audit_log_event_context.py
workos/types/audit_logs/audit_log_event_target.py
workos/types/audit_logs/audit_log_export.py
workos/types/audit_logs/audit_log_metadata.py
workos/types/directory_sync/__init__.py
workos/types/directory_sync/directory.py
workos/types/directory_sync/directory_group.py
workos/types/directory_sync/directory_state.py
workos/types/directory_sync/directory_type.py
workos/types/directory_sync/directory_user.py
workos/types/directory_sync/list_filters.py
workos/types/events/__init__.py
workos/types/events/authentication_payload.py
workos/types/events/connection_payload_with_legacy_fields.py
workos/types/events/directory_group_membership_payload.py
workos/types/events/directory_group_with_previous_attributes.py
workos/types/events/directory_payload.py
workos/types/events/directory_payload_with_legacy_fields.py
workos/types/events/directory_user_with_previous_attributes.py
workos/types/events/event.py
workos/types/events/event_model.py
workos/types/events/event_type.py
workos/types/events/list_filters.py
workos/types/events/organization_domain_verification_failed_payload.py
workos/types/events/previous_attributes.py
workos-5.37.0.dist-info/LICENSE
workos-5.37.0.dist-info/METADATA
workos-5.37.0.dist-info/WHEEL
workos-5.37.0.dist-info/top_level.txt
workos-5.37.0.dist-info/RECORD
