Metadata-Version: 2.1
Name: workos
Version: 5.37.0
Summary: WorkOS Python Client
Home-page: https://github.com/workos-inc/workos-python
Author: WorkOS
Author-email: team@workos.com
License: MIT
Classifier: Development Status :: 5 - Production/Stable
Classifier: Intended Audience :: Developers
Classifier: License :: OSI Approved :: MIT License
Classifier: Operating System :: OS Independent
Classifier: Programming Language :: Python
Classifier: Programming Language :: Python :: 3
Classifier: Programming Language :: Python :: 3.8
Classifier: Programming Language :: Python :: 3.9
Classifier: Programming Language :: Python :: 3.10
Classifier: Programming Language :: Python :: 3.11
Classifier: Programming Language :: Python :: 3.12
License-File: LICENSE
Requires-Dist: cryptography >=44.0.2
Requires-Dist: httpx >=0.28.1
Requires-Dist: pydantic >=2.10.4
Requires-Dist: PyJWT <2.10,>=2.9.0 ; python_version == "3.8"
Requires-Dist: PyJWT >=2.10.0 ; python_version > "3.8"
Provides-Extra: dev
Requires-Dist: black ==24.4.2 ; extra == 'dev'
Requires-Dist: flake8 ==7.1.1 ; extra == 'dev'
Requires-Dist: httpx ~=0.28.1 ; extra == 'dev'
Requires-Dist: mypy ==1.14.1 ; extra == 'dev'
Requires-Dist: pytest-asyncio ==0.23.8 ; extra == 'dev'
Requires-Dist: pytest-cov ==5.0.0 ; extra == 'dev'
Requires-Dist: pytest ==8.3.4 ; extra == 'dev'
Requires-Dist: six ==1.17.0 ; extra == 'dev'
Requires-Dist: twine ==5.1.1 ; extra == 'dev'
